LICENSE
NOTICE
README.md
setup.py
pyqldb/__init__.py
pyqldb.egg-info/PKG-INFO
pyqldb.egg-info/SOURCES.txt
pyqldb.egg-info/dependency_links.txt
pyqldb.egg-info/requires.txt
pyqldb.egg-info/top_level.txt
pyqldb/communication/__init__.py
pyqldb/communication/session_client.py
pyqldb/config/__init__.py
pyqldb/config/retry_config.py
pyqldb/cursor/__init__.py
pyqldb/cursor/buffered_cursor.py
pyqldb/cursor/read_ahead_cursor.py
pyqldb/cursor/stream_cursor.py
pyqldb/driver/__init__.py
pyqldb/driver/qldb_driver.py
pyqldb/errors/__init__.py
pyqldb/execution/__init__.py
pyqldb/execution/executable.py
pyqldb/execution/executor.py
pyqldb/session/__init__.py
pyqldb/session/qldb_session.py
pyqldb/transaction/__init__.py
pyqldb/transaction/transaction.py
pyqldb/util/__init__.py
pyqldb/util/atomic_integer.py
pyqldb/util/qldb_hash.py
pyqldb/util/retry.py