Metadata-Version: 2.1
Name: pyqldb
Version: 3.2.3
Summary: Python driver for Amazon QLDB
Author: Amazon Web Services
License: Apache License 2.0
Classifier: Intended Audience :: Developers
Classifier: License :: OSI Approved :: Apache Software License
Classifier: Programming Language :: Python
Classifier: Programming Language :: Python :: 3.6
Classifier: Programming Language :: Python :: 3.7
Classifier: Programming Language :: Python :: 3.8
License-File: LICENSE
License-File: NOTICE
